example_pkg/__init__.py
example_pkg_ANBARIEF-0.0.1.dist-info/METADATA
example_pkg_ANBARIEF-0.0.1.dist-info/WHEEL
example_pkg_ANBARIEF-0.0.1.dist-info/top_level.txt
example_pkg_ANBARIEF-0.0.1.dist-info/RECORD
