Metadata-Version: 2.1
Name: example-pkg-ANBARIEF
Version: 0.0.1
Summary: blablabla
Home-page: https://github.com/pypa/sampleproject
Author: Arief Anbiya
Author-email: anbarief@live.com
License: UNKNOWN
Platform: UNKNOWN
Classifier: Programming Language :: Python :: 3
Classifier: License :: OSI Approved :: MIT License
Classifier: Operating System :: OS Independent
Requires-Python: >=3.6
